llamass/__init__.py
llamass/_nbdev.py
llamass/core.py
llamass-0.0.1.dist-info/LICENSE
llamass-0.0.1.dist-info/METADATA
llamass-0.0.1.dist-info/WHEEL
llamass-0.0.1.dist-info/entry_points.txt
llamass-0.0.1.dist-info/top_level.txt
llamass-0.0.1.dist-info/RECORD
